{"connect":{"statusCode":200,"response":{"id":"","name":"OKCoin","private":false,"enableRateLimit":true,"countries":["CN","US"],"rateLimit":1000,"has":{"loadMarkets":"true","cancelAllOrders":"false","cancelOrder":"true","cancelOrders":"false","CORS":"false","createDepositAddress":"false","createLimitOrder":"true","createMarketOrder":"true","createOrder":"true","deposit":"false","editOrder":"emulated","fetchBalance":"true","fetchBidsAsks":"false","fetchClosedOrders":"true","fetchCurrencies":"false","fetchDepositAddress":"true","fetchDeposits":"true","fetchFundingFees":"false","fetchL2OrderBook":"true","fetchLedger":"true","fetchMarkets":"true","fetchMyTrades":"true","fetchOHLCV":"true","fetchOpenOrders":"true","fetchOrder":"true","fetchOrderBook":"true","fetchOrderBooks":"false","fetchOrders":"false","fetchOrderTrades":"true","fetchStatus":"emulated","fetchTicker":"true","fetchTickers":"true","fetchTime":"true","fetchTrades":"true","fetchTradingFee":"false","fetchTradingFees":"false","fetchTradingLimits":"false","fetchTransactions":"false","fetchWithdrawals":"true","privateAPI":"true","publicAPI":"true","withdraw":"true","futures":"true"},"urls":{"logo":"https://user-images.githubusercontent.com/1294454/27766791-89ffb502-5ee5-11e7-8a5b-c5950b68ac65.jpg","api":{"rest":"https://www.{hostname}"},"www":"https://www.okcoin.com","doc":"https://www.okcoin.com/docs/en/","fees":"https://www.okcoin.com/coin-fees","referral":"https://www.okcoin.com/account/register?flag=activity&channelId=600001513","test":{"rest":"https://testnet.okex.com"}}}},"markets":{"statusCode":200,"response":[{"id":"BTC-USD","symbol":"BTC/USD","base":"BTC","quote":"USD","info":{"base_currency":"BTC","instrument_id":"BTC-USD","min_size":"0.001","quote_currency":"USD","size_increment":"0.0001","tick_size":"0.01"},"limits":{"amount":{"min":0.001},"price":{"min":0.01},"cost":{"min":0.01}},"precision":{"amount":0.0001,"price":0.01}},{"id":"LTC-USD","symbol":"LTC/USD","base":"LTC","quote":"USD","info":{"base_currency":"LTC","instrument_id":"LTC-USD","min_size":"0.1","quote_currency":"USD","size_increment":"0.0001","tick_size":"0.01"},"limits":{"amount":{"min":0.1},"price":{"min":0.01},"cost":{"min":0.01}},"precision":{"amount":0.0001,"price":0.01}},{"id":"ETH-USD","symbol":"ETH/USD","base":"ETH","quote":"USD","info":{"base_currency":"ETH","instrument_id":"ETH-USD","min_size":"0.01","quote_currency":"USD","size_increment":"0.0001","tick_size":"0.01"},"limits":{"amount":{"min":0.01},"price":{"min":0.01},"cost":{"min":0.01}},"precision":{"amount":0.0001,"price":0.01}},{"id":"ETC-USD","symbol":"ETC/USD","base":"ETC","quote":"USD","info":{"base_currency":"ETC","instrument_id":"ETC-USD","min_size":"0.1","quote_currency":"USD","size_increment":"0.0001","tick_size":"0.001"},"limits":{"amount":{"min":0.1},"price":{"min":0.001},"cost":{"min":0.001}},"precision":{"amount":0.0001,"price":0.001}},{"id":"TUSD-USD","symbol":"TUSD/USD","base":"TUSD","quote":"USD","info":{"base_currency":"TUSD","instrument_id":"TUSD-USD","min_size":"0.01","quote_currency":"USD","size_increment":"0.0001","tick_size":"0.0001"},"limits":{"amount":{"min":0.01},"price":{"min":0.0001},"cost":{"min":0.0001}},"precision":{"amount":0.0001,"price":0.0001}},{"id":"CELO-USD","symbol":"CELO/USD","base":"CELO","quote":"USD","info":{"base_currency":"CELO","instrument_id":"CELO-USD","min_size":"0.1","quote_currency":"USD","size_increment":"0.0001","tick_size":"0.001"},"limits":{"amount":{"min":0.1},"price":{"min":0.001},"cost":{"min":0.001}},"precision":{"amount":0.0001,"price":0.001}},{"id":"BCH-USD","symbol":"BCH/USD","base":"BCH","quote":"USD","info":{"base_currency":"BCH","instrument_id":"BCH-USD","min_size":"0.01","quote_currency":"USD","size_increment":"0.0001","tick_size":"0.01"},"limits":{"amount":{"min":0.01},"price":{"min":0.01},"cost":{"min":0.01}},"precision":{"amount":0.0001,"price":0.01}},{"id":"EOS-USD","symbol":"EOS/USD","base":"EOS","quote":"USD","info":{"base_currency":"EOS","instrument_id":"EOS-USD","min_size":"0.1","quote_currency":"USD","size_increment":"0.0001","tick_size":"0.001"},"limits":{"amount":{"min":0.1},"price":{"min":0.001},"cost":{"min":0.001}},"precision":{"amount":0.0001,"price":0.001}},{"id":"XRP-USD","symbol":"XRP/USD","base":"XRP","quote":"USD","info":{"base_currency":"XRP","instrument_id":"XRP-USD","min_size":"1","quote_currency":"USD","size_increment":"0.001","tick_size":"0.0001"},"limits":{"amount":{"min":1},"price":{"min":0.0001},"cost":{"min":0.0001}},"precision":{"amount":0.001,"price":0.0001}},{"id":"TRX-USD","symbol":"TRX/USD","base":"TRX","quote":"USD","info":{"base_currency":"TRX","instrument_id":"TRX-USD","min_size":"1","quote_currency":"USD","size_increment":"0.0001","tick_size":"0.00001"},"limits":{"amount":{"min":1},"price":{"min":0.00001},"cost":{"min":0.00001}},"precision":{"amount":0.0001,"price":0.00001}},{"id":"BSV-USD","symbol":"BSV/USD","base":"BSV","quote":"USD","info":{"base_currency":"BSV","instrument_id":"BSV-USD","min_size":"0.01","quote_currency":"USD","size_increment":"0.0001","tick_size":"0.01"},"limits":{"amount":{"min":0.01},"price":{"min":0.01},"cost":{"min":0.01}},"precision":{"amount":0.0001,"price":0.01}},{"id":"USDT-USD","symbol":"USDT/USD","base":"USDT","quote":"USD","info":{"base_currency":"USDT","instrument_id":"USDT-USD","min_size":"1","quote_currency":"USD","size_increment":"0.0001","tick_size":"0.0001"},"limits":{"amount":{"min":1},"price":{"min":0.0001},"cost":{"min":0.0001}},"precision":{"amount":0.0001,"price":0.0001}},{"id":"USDK-USD","symbol":"USDK/USD","base":"USDK","quote":"USD","info":{"base_currency":"USDK","instrument_id":"USDK-USD","min_size":"0.01","quote_currency":"USD","size_increment":"0.0001","tick_size":"0.0001"},"limits":{"amount":{"min":0.01},"price":{"min":0.0001},"cost":{"min":0.0001}},"precision":{"amount":0.0001,"price":0.0001}},{"id":"USDC-USD","symbol":"USDC/USD","base":"USDC","quote":"USD","info":{"base_currency":"USDC","instrument_id":"USDC-USD","min_size":"0.1","quote_currency":"USD","size_increment":"0.0001","tick_size":"0.0001"},"limits":{"amount":{"min":0.1},"price":{"min":0.0001},"cost":{"min":0.0001}},"precision":{"amount":0.0001,"price":0.0001}},{"id":"DAI-USD","symbol":"DAI/USD","base":"DAI","quote":"USD","info":{"base_currency":"DAI","instrument_id":"DAI-USD","min_size":"1","quote_currency":"USD","size_increment":"0.0001","tick_size":"0.0001"},"limits":{"amount":{"min":1},"price":{"min":0.0001},"cost":{"min":0.0001}},"precision":{"amount":0.0001,"price":0.0001}},{"id":"EURS-USD","symbol":"EURS/USD","base":"EURS","quote":"USD","info":{"base_currency":"EURS","instrument_id":"EURS-USD","min_size":"0.01","quote_currency":"USD","size_increment":"0.0001","tick_size":"0.0001"},"limits":{"amount":{"min":0.01},"price":{"min":0.0001},"cost":{"min":0.0001}},"precision":{"amount":0.0001,"price":0.0001}},{"id":"HBAR-USD","symbol":"HBAR/USD","base":"HBAR","quote":"USD","info":{"base_currency":"HBAR","instrument_id":"HBAR-USD","min_size":"1","quote_currency":"USD","size_increment":"0.0001","tick_size":"0.0001"},"limits":{"amount":{"min":1},"price":{"min":0.0001},"cost":{"min":0.0001}},"precision":{"amount":0.0001,"price":0.0001}},{"id":"PAX-USD","symbol":"PAX/USD","base":"PAX","quote":"USD","info":{"base_currency":"PAX","instrument_id":"PAX-USD","min_size":"0.1","quote_currency":"USD","size_increment":"0.0001","tick_size":"0.0001"},"limits":{"amount":{"min":0.1},"price":{"min":0.0001},"cost":{"min":0.0001}},"precision":{"amount":0.0001,"price":0.0001}},{"id":"BTC-USDT","symbol":"BTC/USDT","base":"BTC","quote":"USDT","info":{"base_currency":"BTC","instrument_id":"BTC-USDT","min_size":"0.001","quote_currency":"USDT","size_increment":"0.0001","tick_size":"0.1"},"limits":{"amount":{"min":0.001},"price":{"min":0.1},"cost":{"min":0.1}},"precision":{"amount":0.0001,"price":0.1}},{"id":"BTC-SGD","symbol":"BTC/SGD","base":"BTC","quote":"SGD","info":{"base_currency":"BTC","instrument_id":"BTC-SGD","min_size":"0.001","quote_currency":"SGD","size_increment":"0.0001","tick_size":"0.01"},"limits":{"amount":{"min":0.001},"price":{"min":0.01},"cost":{"min":0.01}},"precision":{"amount":0.0001,"price":0.01}},{"id":"ETH-SGD","symbol":"ETH/SGD","base":"ETH","quote":"SGD","info":{"base_currency":"ETH","instrument_id":"ETH-SGD","min_size":"0.01","quote_currency":"SGD","size_increment":"0.0001","tick_size":"0.01"},"limits":{"amount":{"min":0.01},"price":{"min":0.01},"cost":{"min":0.01}},"precision":{"amount":0.0001,"price":0.01}},{"id":"BTC-EUR","symbol":"BTC/EUR","base":"BTC","quote":"EUR","info":{"base_currency":"BTC","instrument_id":"BTC-EUR","min_size":"0.001","quote_currency":"EUR","size_increment":"0.0001","tick_size":"0.01"},"limits":{"amount":{"min":0.001},"price":{"min":0.01},"cost":{"min":0.01}},"precision":{"amount":0.0001,"price":0.01}},{"id":"BTC-EURS","symbol":"BTC/EURS","base":"BTC","quote":"EURS","info":{"base_currency":"BTC","instrument_id":"BTC-EURS","min_size":"0.001","quote_currency":"EURS","size_increment":"0.0001","tick_size":"0.01"},"limits":{"amount":{"min":0.001},"price":{"min":0.01},"cost":{"min":0.01}},"precision":{"amount":0.0001,"price":0.01}},{"id":"ETH-EUR","symbol":"ETH/EUR","base":"ETH","quote":"EUR","info":{"base_currency":"ETH","instrument_id":"ETH-EUR","min_size":"0.01","quote_currency":"EUR","size_increment":"0.0001","tick_size":"0.01"},"limits":{"amount":{"min":0.01},"price":{"min":0.01},"cost":{"min":0.01}},"precision":{"amount":0.0001,"price":0.01}},{"id":"BCH-EUR","symbol":"BCH/EUR","base":"BCH","quote":"EUR","info":{"base_currency":"BCH","instrument_id":"BCH-EUR","min_size":"0.01","quote_currency":"EUR","size_increment":"0.0001","tick_size":"0.01"},"limits":{"amount":{"min":0.01},"price":{"min":0.01},"cost":{"min":0.01}},"precision":{"amount":0.0001,"price":0.01}},{"id":"EURS-EUR","symbol":"EURS/EUR","base":"EURS","quote":"EUR","info":{"base_currency":"EURS","instrument_id":"EURS-EUR","min_size":"0.01","quote_currency":"EUR","size_increment":"0.0001","tick_size":"0.0001"},"limits":{"amount":{"min":0.01},"price":{"min":0.0001},"cost":{"min":0.0001}},"precision":{"amount":0.0001,"price":0.0001}}]},"ticker":{"statusCode":200,"response":{"symbol":"BTC/USD","timestamp":1595254253885,"datetime":"2020-07-20T14:10:53.885Z","high":9237.3,"low":9120.41,"bid":9160.3,"ask":9160.31,"close":9160.3,"last":9160.3,"baseVolume":460.3844,"quoteVolume":4222160.88,"info":{"best_ask":"9160.31","best_bid":"9160.3","instrument_id":"BTC-USD","product_id":"BTC-USD","last":"9160.3","last_qty":"0.0063","ask":"9160.31","best_ask_size":"0.3274","bid":"9160.3","best_bid_size":"2.0046","open_24h":"9125.53","high_24h":"9237.3","low_24h":"9120.41","base_volume_24h":"460.3844","timestamp":"2020-07-20T14:10:53.885Z","quote_volume_24h":"4222160.88"}}},"tickers":{"statusCode":200,"response":[{"symbol":"BCH/EUR","timestamp":1595254203111,"datetime":"2020-07-20T14:10:03.111Z","high":198.2,"low":196.4,"bid":197.38,"ask":197.81,"close":196.4,"last":196.4,"baseVolume":39.0177,"quoteVolume":7690.1338,"info":{"best_ask":"197.81","best_bid":"197.38","instrument_id":"BCH-EUR","product_id":"BCH-EUR","last":"196.4","last_qty":"0","ask":"197.81","best_ask_size":"3.024","bid":"197.38","best_bid_size":"1.126","open_24h":"197.2","high_24h":"198.2","low_24h":"196.4","base_volume_24h":"39.0177","timestamp":"2020-07-20T14:10:03.111Z","quote_volume_24h":"7690.1338"}},{"symbol":"BCH/USD","timestamp":1595254203292,"datetime":"2020-07-20T14:10:03.292Z","high":228.51,"low":222.38,"bid":225.08,"ask":225.26,"close":224.91,"last":224.91,"baseVolume":88.0083,"quoteVolume":19883.5431,"info":{"best_ask":"225.26","best_bid":"225.08","instrument_id":"BCH-USD","product_id":"BCH-USD","last":"224.91","last_qty":"0","ask":"225.26","best_ask_size":"1.87","bid":"225.08","best_bid_size":"1.87","open_24h":"222.38","high_24h":"228.51","low_24h":"222.38","base_volume_24h":"88.0083","timestamp":"2020-07-20T14:10:03.292Z","quote_volume_24h":"19883.5431"}},{"symbol":"BSV/USD","timestamp":1595254203025,"datetime":"2020-07-20T14:10:03.025Z","high":171.87,"low":164.42,"bid":170.04,"ask":170.34,"close":169.62,"last":169.62,"baseVolume":17.1798,"quoteVolume":2924.4922,"info":{"best_ask":"170.34","best_bid":"170.04","instrument_id":"BSV-USD","product_id":"BSV-USD","last":"169.62","last_qty":"0","ask":"170.34","best_ask_size":"3.061","bid":"170.04","best_bid_size":"0.321","open_24h":"164.42","high_24h":"171.87","low_24h":"164.42","base_volume_24h":"17.1798","timestamp":"2020-07-20T14:10:03.025Z","quote_volume_24h":"2924.4922"}},{"symbol":"BTC/EUR","timestamp":1595254203117,"datetime":"2020-07-20T14:10:03.117Z","high":8082,"low":7999.22,"bid":8032.52,"ask":8043.75,"close":8031.02,"last":8031.02,"baseVolume":31.451,"quoteVolume":252837.184,"info":{"best_ask":"8043.75","best_bid":"8032.52","instrument_id":"BTC-EUR","product_id":"BTC-EUR","last":"8031.02","last_qty":"0","ask":"8043.75","best_ask_size":"3.9396","bid":"8032.52","best_bid_size":"0.014","open_24h":"8002.24","high_24h":"8082","low_24h":"7999.22","base_volume_24h":"31.451","timestamp":"2020-07-20T14:10:03.117Z","quote_volume_24h":"252837.184"}},{"symbol":"BTC/EURS","timestamp":1595254203036,"datetime":"2020-07-20T14:10:03.036Z","high":8065.4,"low":8065.4,"bid":8034.13,"ask":8056.08,"close":8065.4,"last":8065.4,"baseVolume":0,"quoteVolume":0,"info":{"best_ask":"8056.08","best_bid":"8034.13","instrument_id":"BTC-EURS","product_id":"BTC-EURS","last":"8065.4","last_qty":"0","ask":"8056.08","best_ask_size":"0.1","bid":"8034.13","best_bid_size":"0.021","open_24h":"8065.4","high_24h":"8065.4","low_24h":"8065.4","base_volume_24h":"0","timestamp":"2020-07-20T14:10:03.036Z","quote_volume_24h":"0"}},{"symbol":"BTC/SGD","timestamp":1595254203301,"datetime":"2020-07-20T14:10:03.301Z","high":13282.88,"low":13282.88,"bid":12724.84,"ask":12754.27,"close":13282.88,"last":13282.88,"baseVolume":0,"quoteVolume":0,"info":{"best_ask":"12754.27","best_bid":"12724.84","instrument_id":"BTC-SGD","product_id":"BTC-SGD","last":"13282.88","last_qty":"0","ask":"12754.27","best_ask_size":"0.006","bid":"12724.84","best_bid_size":"0.022","open_24h":"13282.88","high_24h":"13282.88","low_24h":"13282.88","base_volume_24h":"0","timestamp":"2020-07-20T14:10:03.301Z","quote_volume_24h":"0"}},{"symbol":"BTC/USD","timestamp":1595254253885,"datetime":"2020-07-20T14:10:53.885Z","high":9237.3,"low":9120.41,"bid":9160.3,"ask":9160.31,"close":9160.3,"last":9160.3,"baseVolume":460.3844,"quoteVolume":4222160.8893,"info":{"best_ask":"9160.31","best_bid":"9160.3","instrument_id":"BTC-USD","product_id":"BTC-USD","last":"9160.3","last_qty":"0.0063","ask":"9160.31","best_ask_size":"0.3274","bid":"9160.3","best_bid_size":"2.0046","open_24h":"9125.53","high_24h":"9237.3","low_24h":"9120.41","base_volume_24h":"460.3844","timestamp":"2020-07-20T14:10:53.885Z","quote_volume_24h":"4222160.8893"}},{"symbol":"BTC/USDT","timestamp":1595254203328,"datetime":"2020-07-20T14:10:03.328Z","high":9218.5,"low":9139.5,"bid":9154.2,"ask":9170.4,"close":9218.5,"last":9218.5,"baseVolume":0.866,"quoteVolume":7948.9339,"info":{"best_ask":"9170.4","best_bid":"9154.2","instrument_id":"BTC-USDT","product_id":"BTC-USDT","last":"9218.5","last_qty":"0","ask":"9170.4","best_ask_size":"0.3673","bid":"9154.2","best_bid_size":"0.4075","open_24h":"9139.5","high_24h":"9218.5","low_24h":"9139.5","base_volume_24h":"0.866","timestamp":"2020-07-20T14:10:03.328Z","quote_volume_24h":"7948.9339"}},{"symbol":"CELO/USD","timestamp":1595254203119,"datetime":"2020-07-20T14:10:03.119Z","high":1.791,"low":1.791,"bid":1.691,"ask":1.783,"close":1.791,"last":1.791,"baseVolume":0,"quoteVolume":0,"info":{"best_ask":"1.783","best_bid":"1.691","instrument_id":"CELO-USD","product_id":"CELO-USD","last":"1.791","last_qty":"0","ask":"1.783","best_ask_size":"5.631","bid":"1.691","best_bid_size":"100","open_24h":"1.791","high_24h":"1.791","low_24h":"1.791","base_volume_24h":"0","timestamp":"2020-07-20T14:10:03.119Z","quote_volume_24h":"0"}},{"symbol":"DAI/USD","timestamp":1595254203470,"datetime":"2020-07-20T14:10:03.470Z","high":1.0101,"low":1.007,"bid":1.0081,"ask":1.009,"close":1.007,"last":1.007,"baseVolume":14222.9272,"quoteVolume":14336.1569,"info":{"best_ask":"1.009","best_bid":"1.0081","instrument_id":"DAI-USD","product_id":"DAI-USD","last":"1.007","last_qty":"0","ask":"1.009","best_ask_size":"500","bid":"1.0081","best_bid_size":"500","open_24h":"1.0101","high_24h":"1.0101","low_24h":"1.007","base_volume_24h":"14222.9272","timestamp":"2020-07-20T14:10:03.470Z","quote_volume_24h":"14336.1569"}},{"symbol":"EOS/USD","timestamp":1595254203034,"datetime":"2020-07-20T14:10:03.034Z","high":2.609,"low":2.484,"bid":2.577,"ask":2.58,"close":2.571,"last":2.571,"baseVolume":3513.9402,"quoteVolume":8987.549,"info":{"best_ask":"2.58","best_bid":"2.577","instrument_id":"EOS-USD","product_id":"EOS-USD","last":"2.571","last_qty":"0","ask":"2.58","best_ask_size":"669.707","bid":"2.577","best_bid_size":"1371.198","open_24h":"2.484","high_24h":"2.609","low_24h":"2.484","base_volume_24h":"3513.9402","timestamp":"2020-07-20T14:10:03.034Z","quote_volume_24h":"8987.549"}},{"symbol":"ETC/USD","timestamp":1595254203010,"datetime":"2020-07-20T14:10:03.010Z","high":6,"low":5.989,"bid":6.084,"ask":6.096,"close":6,"last":6,"baseVolume":1,"quoteVolume":6,"info":{"best_ask":"6.096","best_bid":"6.084","instrument_id":"ETC-USD","product_id":"ETC-USD","last":"6","last_qty":"0","ask":"6.096","best_ask_size":"29.4","bid":"6.084","best_bid_size":"5.99","open_24h":"5.989","high_24h":"6","low_24h":"5.989","base_volume_24h":"1","timestamp":"2020-07-20T14:10:03.010Z","quote_volume_24h":"6"}},{"symbol":"ETH/EUR","timestamp":1595254203460,"datetime":"2020-07-20T14:10:03.460Z","high":209.49,"low":206.14,"bid":208.62,"ask":208.97,"close":208.45,"last":208.45,"baseVolume":51.7378,"quoteVolume":10768.4422,"info":{"best_ask":"208.97","best_bid":"208.62","instrument_id":"ETH-EUR","product_id":"ETH-EUR","last":"208.45","last_qty":"0","ask":"208.97","best_ask_size":"0.6567","bid":"208.62","best_bid_size":"44.308","open_24h":"206.14","high_24h":"209.49","low_24h":"206.14","base_volume_24h":"51.7378","timestamp":"2020-07-20T14:10:03.460Z","quote_volume_24h":"10768.4422"}},{"symbol":"ETH/SGD","timestamp":1595254203040,"datetime":"2020-07-20T14:10:03.040Z","high":308.39,"low":308.39,"bid":330.53,"ask":331.32,"close":308.39,"last":308.39,"baseVolume":0,"quoteVolume":0,"info":{"best_ask":"331.32","best_bid":"330.53","instrument_id":"ETH-SGD","product_id":"ETH-SGD","last":"308.39","last_qty":"0","ask":"331.32","best_ask_size":"3.0077","bid":"330.53","best_bid_size":"3.0117","open_24h":"308.39","high_24h":"308.39","low_24h":"308.39","base_volume_24h":"0","timestamp":"2020-07-20T14:10:03.040Z","quote_volume_24h":"0"}},{"symbol":"ETH/USD","timestamp":1595254210458,"datetime":"2020-07-20T14:10:10.458Z","high":239.82,"low":233.58,"bid":238.1,"ask":238.11,"close":238.1,"last":238.1,"baseVolume":2962.4356,"quoteVolume":704489.8029,"info":{"best_ask":"238.11","best_bid":"238.1","instrument_id":"ETH-USD","product_id":"ETH-USD","last":"238.1","last_qty":"0.4199","ask":"238.11","best_ask_size":"3.6993","bid":"238.1","best_bid_size":"0.4199","open_24h":"233.81","high_24h":"239.82","low_24h":"233.58","base_volume_24h":"2962.4356","timestamp":"2020-07-20T14:10:10.458Z","quote_volume_24h":"704489.8029"}},{"symbol":"EURS/EUR","timestamp":1595254203513,"datetime":"2020-07-20T14:10:03.513Z","high":0.999,"low":0.999,"bid":0.999,"ask":1.0001,"close":0.999,"last":0.999,"baseVolume":0,"quoteVolume":0,"info":{"best_ask":"1.0001","best_bid":"0.999","instrument_id":"EURS-EUR","product_id":"EURS-EUR","last":"0.999","last_qty":"0","ask":"1.0001","best_ask_size":"1167.57","bid":"0.999","best_bid_size":"1832.43","open_24h":"0.999","high_24h":"0.999","low_24h":"0.999","base_volume_24h":"0","timestamp":"2020-07-20T14:10:03.513Z","quote_volume_24h":"0"}},{"symbol":"EURS/USD","timestamp":1595254203333,"datetime":"2020-07-20T14:10:03.333Z","high":1,"low":1,"bid":0.0111,"ask":29.495,"close":1,"last":1,"baseVolume":0,"quoteVolume":0,"info":{"best_ask":"29.495","best_bid":"0.0111","instrument_id":"EURS-USD","product_id":"EURS-USD","last":"1","last_qty":"0","ask":"29.495","best_ask_size":"69.2067","bid":"0.0111","best_bid_size":"405.8379","open_24h":"1","high_24h":"1","low_24h":"1","base_volume_24h":"0","timestamp":"2020-07-20T14:10:03.333Z","quote_volume_24h":"0"}},{"symbol":"HBAR/USD","timestamp":1595254203464,"datetime":"2020-07-20T14:10:03.464Z","high":0.0408,"low":0.0394,"bid":0.0401,"ask":0.0402,"close":0.0401,"last":0.0401,"baseVolume":1516664.8781,"quoteVolume":61088.4418,"info":{"best_ask":"0.0402","best_bid":"0.0401","instrument_id":"HBAR-USD","product_id":"HBAR-USD","last":"0.0401","last_qty":"0","ask":"0.0402","best_ask_size":"25866.5835","bid":"0.0401","best_bid_size":"34133.4165","open_24h":"0.0395","high_24h":"0.0408","low_24h":"0.0394","base_volume_24h":"1516664.8781","timestamp":"2020-07-20T14:10:03.464Z","quote_volume_24h":"61088.4418"}},{"symbol":"LTC/USD","timestamp":1595254203283,"datetime":"2020-07-20T14:10:03.283Z","high":42.88,"low":42.09,"bid":42.26,"ask":42.27,"close":42.26,"last":42.26,"baseVolume":1936.5081,"quoteVolume":82248.6313,"info":{"best_ask":"42.27","best_bid":"42.26","instrument_id":"LTC-USD","product_id":"LTC-USD","last":"42.26","last_qty":"0","ask":"42.27","best_ask_size":"55.757","bid":"42.26","best_bid_size":"2.3663","open_24h":"42.14","high_24h":"42.88","low_24h":"42.09","base_volume_24h":"1936.5081","timestamp":"2020-07-20T14:10:03.283Z","quote_volume_24h":"82248.6313"}},{"symbol":"PAX/USD","timestamp":1595254203289,"datetime":"2020-07-20T14:10:03.289Z","high":1.0008,"low":1.0008,"bid":0.9989,"ask":1.0015,"close":1.0008,"last":1.0008,"baseVolume":0,"quoteVolume":0,"info":{"best_ask":"1.0015","best_bid":"0.9989","instrument_id":"PAX-USD","product_id":"PAX-USD","last":"1.0008","last_qty":"0","ask":"1.0015","best_ask_size":"66.044","bid":"0.9989","best_bid_size":"23182.3916","open_24h":"1.0008","high_24h":"1.0008","low_24h":"1.0008","base_volume_24h":"0","timestamp":"2020-07-20T14:10:03.289Z","quote_volume_24h":"0"}},{"symbol":"TRX/USD","timestamp":1595254203322,"datetime":"2020-07-20T14:10:03.322Z","high":0.01701,"low":0.01701,"bid":0.01724,"ask":0.01732,"close":0.01701,"last":0.01701,"baseVolume":0,"quoteVolume":0,"info":{"best_ask":"0.01732","best_bid":"0.01724","instrument_id":"TRX-USD","product_id":"TRX-USD","last":"0.01701","last_qty":"0","ask":"0.01732","best_ask_size":"3622.05","bid":"0.01724","best_bid_size":"1317388.8986","open_24h":"0.01701","high_24h":"0.01701","low_24h":"0.01701","base_volume_24h":"0","timestamp":"2020-07-20T14:10:03.322Z","quote_volume_24h":"0"}},{"symbol":"TUSD/USD","timestamp":1595254203286,"datetime":"2020-07-20T14:10:03.286Z","high":0.9993,"low":0.9993,"bid":0.999,"ask":1.0007,"close":0.9993,"last":0.9993,"baseVolume":0,"quoteVolume":0,"info":{"best_ask":"1.0007","best_bid":"0.999","instrument_id":"TUSD-USD","product_id":"TUSD-USD","last":"0.9993","last_qty":"0","ask":"1.0007","best_ask_size":"1500","bid":"0.999","best_bid_size":"3227.6268","open_24h":"0.9993","high_24h":"0.9993","low_24h":"0.9993","base_volume_24h":"0","timestamp":"2020-07-20T14:10:03.286Z","quote_volume_24h":"0"}},{"symbol":"USDC/USD","timestamp":1595254203022,"datetime":"2020-07-20T14:10:03.022Z","high":1.0007,"low":0.9996,"bid":0.9996,"ask":1.0011,"close":0.9996,"last":0.9996,"baseVolume":519.9192,"quoteVolume":520.2616,"info":{"best_ask":"1.0011","best_bid":"0.9996","instrument_id":"USDC-USD","product_id":"USDC-USD","last":"0.9996","last_qty":"0","ask":"1.0011","best_ask_size":"1500","bid":"0.9996","best_bid_size":"3001.2004","open_24h":"1.0005","high_24h":"1.0007","low_24h":"0.9996","base_volume_24h":"519.9192","timestamp":"2020-07-20T14:10:03.022Z","quote_volume_24h":"520.2616"}},{"symbol":"USDK/USD","timestamp":1595254203298,"datetime":"2020-07-20T14:10:03.298Z","high":1.0001,"low":1,"bid":1,"ask":1.0001,"close":1,"last":1,"baseVolume":354.1017,"quoteVolume":354.1181,"info":{"best_ask":"1.0001","best_bid":"1","instrument_id":"USDK-USD","product_id":"USDK-USD","last":"1","last_qty":"0","ask":"1.0001","best_ask_size":"1131928.8398","bid":"1","best_bid_size":"100837.0902","open_24h":"1","high_24h":"1.0001","low_24h":"1","base_volume_24h":"354.1017","timestamp":"2020-07-20T14:10:03.298Z","quote_volume_24h":"354.1181"}},{"symbol":"USDT/USD","timestamp":1595254203045,"datetime":"2020-07-20T14:10:03.045Z","high":1,"low":0.9992,"bid":0.9998,"ask":0.9999,"close":0.9999,"last":0.9999,"baseVolume":2566513.6509,"quoteVolume":2565675.1518,"info":{"best_ask":"0.9999","best_bid":"0.9998","instrument_id":"USDT-USD","product_id":"USDT-USD","last":"0.9999","last_qty":"0","ask":"0.9999","best_ask_size":"44271.4383","bid":"0.9998","best_bid_size":"300","open_24h":"0.9996","high_24h":"1","low_24h":"0.9992","base_volume_24h":"2566513.6509","timestamp":"2020-07-20T14:10:03.045Z","quote_volume_24h":"2565675.1518"}},{"symbol":"XRP/USD","timestamp":1595254203049,"datetime":"2020-07-20T14:10:03.049Z","high":0.2001,"low":0.1963,"bid":0.1973,"ask":0.1974,"close":0.1974,"last":0.1974,"baseVolume":57642.15,"quoteVolume":11477.014,"info":{"best_ask":"0.1974","best_bid":"0.1973","instrument_id":"XRP-USD","product_id":"XRP-USD","last":"0.1974","last_qty":"0","ask":"0.1974","best_ask_size":"1.528","bid":"0.1973","best_bid_size":"13079.918","open_24h":"0.1964","high_24h":"0.2001","low_24h":"0.1963","base_volume_24h":"57642.15","timestamp":"2020-07-20T14:10:03.049Z","quote_volume_24h":"11477.014"}}]},"orderBook":{"statusCode":200,"response":{"bids":[{"price":9160.3,"amount":2.0046},{"price":9159.89,"amount":1.0917},{"price":9159.08,"amount":0.2183},{"price":9158.4,"amount":0.009},{"price":9158.26,"amount":0.115},{"price":9157.62,"amount":0.229},{"price":9157.61,"amount":0.3245},{"price":9157.48,"amount":0.909},{"price":9156.79,"amount":0.001},{"price":9156.77,"amount":0.5417},{"price":9156.57,"amount":0.903},{"price":9155.75,"amount":0.344},{"price":9155.74,"amount":0.001},{"price":9155.72,"amount":0.655},{"price":9155.65,"amount":1.082},{"price":9155.27,"amount":0.0296},{"price":9154.97,"amount":0.2},{"price":9154.74,"amount":0.5449},{"price":9153.51,"amount":0.5445},{"price":9152.63,"amount":0.5455},{"price":9152.43,"amount":0.053},{"price":9152.42,"amount":0.269},{"price":9151.44,"amount":0.18},{"price":9150.33,"amount":0.5356},{"price":9146.86,"amount":0.2956},{"price":9146.52,"amount":2.1866},{"price":9145.61,"amount":0.3754},{"price":9145.29,"amount":0.5},{"price":9144.74,"amount":1.596},{"price":9144.65,"amount":2.799},{"price":9144.28,"amount":0.5},{"price":9142.95,"amount":0.5},{"price":9142.71,"amount":0.011},{"price":9142.48,"amount":0.54},{"price":9142.36,"amount":0.566},{"price":9140.07,"amount":3.05},{"price":9138.5,"amount":1.56},{"price":9138.47,"amount":0.5192},{"price":9138.24,"amount":2.918},{"price":9137.32,"amount":2.887},{"price":9136.96,"amount":1.574},{"price":9136.66,"amount":0.4},{"price":9136.18,"amount":0.5},{"price":9134.34,"amount":0.5112},{"price":9133.58,"amount":0.022},{"price":9133.32,"amount":1.84},{"price":9131,"amount":0.0053},{"price":9129.17,"amount":1.494},{"price":9128,"amount":0.0068},{"price":9126.48,"amount":0.8297},{"price":9125.52,"amount":2.87},{"price":9124.45,"amount":0.033},{"price":9120.4,"amount":0.029},{"price":9115.34,"amount":0.044},{"price":9115.12,"amount":2.7536},{"price":9114.86,"amount":3.031},{"price":9113.31,"amount":0.8418},{"price":9109.26,"amount":0.166},{"price":9106.61,"amount":1.0626},{"price":9103.38,"amount":18.31},{"price":9087.39,"amount":14.718},{"price":9087.11,"amount":0.9135},{"price":9086.8,"amount":0.2548},{"price":9073.19,"amount":0.21},{"price":9057.46,"amount":9.18},{"price":9056.51,"amount":0.0022},{"price":9054.18,"amount":0.198},{"price":9023.22,"amount":5.42},{"price":9000,"amount":0.2},{"price":8931.4,"amount":1.8},{"price":8910,"amount":0.5},{"price":8900,"amount":3.0617},{"price":8888,"amount":0.5},{"price":8870,"amount":0.5},{"price":8850.15,"amount":1.77},{"price":8800,"amount":2.4343},{"price":8790,"amount":0.5},{"price":8750,"amount":0.5406},{"price":8739.92,"amount":0.4877},{"price":8737.14,"amount":73.025},{"price":8715.74,"amount":1.83},{"price":8702.29,"amount":0.001},{"price":8650.47,"amount":0.002},{"price":8650.2,"amount":0.15},{"price":8630,"amount":0.1},{"price":8600,"amount":4},{"price":8550,"amount":0.0491},{"price":8512.12,"amount":0.5873},{"price":8500,"amount":2},{"price":8480,"amount":0.1},{"price":8454.15,"amount":0.001},{"price":8427.48,"amount":0.001},{"price":8378,"amount":0.0105},{"price":8376.75,"amount":0.7823},{"price":8239.92,"amount":0.2427},{"price":8200,"amount":0.0609},{"price":8100,"amount":0.5494},{"price":8039.92,"amount":0.6218},{"price":8000,"amount":1.36},{"price":7939.92,"amount":0.3778},{"price":7839.92,"amount":0.2551},{"price":7800,"amount":0.0137},{"price":7783.53,"amount":0.842},{"price":7739.92,"amount":0.646},{"price":7639.92,"amount":0.6544},{"price":7500,"amount":1.1},{"price":7439.92,"amount":0.2688},{"price":7416,"amount":0.1},{"price":7300,"amount":0.1},{"price":7200,"amount":0.1794},{"price":7139.92,"amount":0.4624},{"price":7000,"amount":1.4301},{"price":6600,"amount":0.01},{"price":6500,"amount":0.567},{"price":6250,"amount":0.1},{"price":6000,"amount":0.1},{"price":5500,"amount":0.1951},{"price":5450,"amount":5.78},{"price":5250,"amount":0.0036},{"price":5000,"amount":2.6144},{"price":4960,"amount":5.6643},{"price":4711,"amount":0.8},{"price":4500,"amount":0.4047},{"price":4300,"amount":0.1713},{"price":4200,"amount":0.6},{"price":4100,"amount":0.3825},{"price":4000,"amount":1.5553},{"price":3910,"amount":2.55},{"price":3810,"amount":1},{"price":3705,"amount":0.0269},{"price":3605,"amount":0.0277},{"price":3505,"amount":0.0285},{"price":3500,"amount":0.5204},{"price":3405,"amount":0.0293},{"price":3305,"amount":0.0302},{"price":3205,"amount":0.0312},{"price":3200,"amount":0.1},{"price":3105,"amount":0.0322},{"price":3100,"amount":0.6223},{"price":3005,"amount":0.0332},{"price":3000,"amount":1},{"price":2905,"amount":0.0344},{"price":2857.6,"amount":0.9265},{"price":2805,"amount":0.0356},{"price":2705,"amount":0.1109},{"price":2605,"amount":0.1151},{"price":2510,"amount":0.5554},{"price":2505,"amount":0.1197},{"price":2405,"amount":0.1247},{"price":2310.91,"amount":0.8},{"price":2305,"amount":0.1301},{"price":2250.91,"amount":0.8821},{"price":2205,"amount":0.136},{"price":2123.19,"amount":0.4289},{"price":2105,"amount":0.1425},{"price":2005,"amount":0.1496},{"price":1810.91,"amount":1.1344},{"price":1320,"amount":0.1},{"price":1310.91,"amount":1.567},{"price":1200,"amount":0.015},{"price":1000,"amount":0.11},{"price":900,"amount":1.432},{"price":816,"amount":1.105},{"price":766,"amount":1.359},{"price":653,"amount":0.05},{"price":600,"amount":0.1},{"price":583,"amount":0.09},{"price":577,"amount":0.13},{"price":573,"amount":0.17},{"price":567,"amount":0.21},{"price":563,"amount":0.19},{"price":388,"amount":0.01},{"price":305.75,"amount":0.01},{"price":303.75,"amount":0.01},{"price":301.75,"amount":0.015},{"price":100,"amount":0.11},{"price":63.28,"amount":0.0126},{"price":24,"amount":0.12},{"price":20,"amount":1},{"price":10,"amount":1},{"price":2,"amount":2},{"price":1.38,"amount":116.2888},{"price":1.05,"amount":3.9371},{"price":1,"amount":24.18},{"price":0.38,"amount":13.1578},{"price":0.15,"amount":12.4633},{"price":0.1,"amount":8757.853},{"price":0.05,"amount":15.7852},{"price":0.04,"amount":30.2317},{"price":0.03,"amount":33.3333},{"price":0.02,"amount":28.5},{"price":0.01,"amount":5032.02}],"asks":[{"price":9160.31,"amount":0.3274},{"price":9160.32,"amount":2.3725},{"price":9160.93,"amount":0.2183},{"price":9161.24,"amount":0.908},{"price":9161.33,"amount":0.3263},{"price":9161.89,"amount":0.3977},{"price":9162.16,"amount":0.927},{"price":9162.43,"amount":0.5409},{"price":9162.62,"amount":0.001},{"price":9163,"amount":0.2151},{"price":9163.07,"amount":1.058},{"price":9163.72,"amount":0.085},{"price":9163.73,"amount":0.229},{"price":9163.74,"amount":0.18},{"price":9163.76,"amount":0.5408},{"price":9164.08,"amount":1.07},{"price":9164.5,"amount":0.001},{"price":9164.88,"amount":0.7358},{"price":9165.01,"amount":0.0347},{"price":9165.82,"amount":2.803},{"price":9165.89,"amount":0.325},{"price":9166.17,"amount":0.5355},{"price":9166.74,"amount":2.998},{"price":9166.99,"amount":0.344},{"price":9167,"amount":1},{"price":9167.63,"amount":0.5458},{"price":9168.11,"amount":0.3799},{"price":9168.8,"amount":0.47},{"price":9169.68,"amount":0.5373},{"price":9171.79,"amount":0.54},{"price":9172.24,"amount":0.291},{"price":9173.79,"amount":0.5},{"price":9174.53,"amount":0.82},{"price":9175.89,"amount":1.502},{"price":9176.23,"amount":0.4808},{"price":9176.82,"amount":0.701},{"price":9179.24,"amount":2.8972},{"price":9179.25,"amount":1.84},{"price":9181.79,"amount":0.0284},{"price":9182.2,"amount":7.53},{"price":9183.21,"amount":0.4},{"price":9183.38,"amount":0.8334},{"price":9183.67,"amount":1.56},{"price":9184.16,"amount":0.0108},{"price":9184.81,"amount":0.249},{"price":9186.01,"amount":0.0446},{"price":9189.31,"amount":0.8232},{"price":9189.54,"amount":2.7313},{"price":9191.46,"amount":1.516},{"price":9197.21,"amount":1.0872},{"price":9197.63,"amount":0.1752},{"price":9197.76,"amount":1.1088},{"price":9198.71,"amount":2.87},{"price":9199.64,"amount":2.967},{"price":9200,"amount":1},{"price":9204.38,"amount":18.31},{"price":9207.56,"amount":2.1721},{"price":9207.88,"amount":0.3008},{"price":9208.23,"amount":0.9815},{"price":9218.24,"amount":0.251},{"price":9227.11,"amount":14.676},{"price":9233.35,"amount":9.18},{"price":9241.09,"amount":0.188},{"price":9279.06,"amount":5.42},{"price":9299.35,"amount":0.1044},{"price":9310,"amount":0.3686},{"price":9350,"amount":6.9975},{"price":9414.94,"amount":1.8},{"price":9500,"amount":0.0295},{"price":9506.7,"amount":1.77},{"price":9550,"amount":6},{"price":9577.36,"amount":73.016},{"price":9600,"amount":12},{"price":9636.92,"amount":1.83},{"price":9645,"amount":0.0122},{"price":9650,"amount":0.01},{"price":9688,"amount":0.5},{"price":9700,"amount":3},{"price":9725,"amount":0.01},{"price":9740,"amount":6},{"price":9750,"amount":6},{"price":9780,"amount":1.3026},{"price":9790,"amount":0.3652},{"price":9798,"amount":0.1095},{"price":9800,"amount":8.04},{"price":9850,"amount":6.03},{"price":9880,"amount":6},{"price":9888,"amount":0.5},{"price":9900,"amount":0.1476},{"price":9910,"amount":6},{"price":9912,"amount":0.01},{"price":9950,"amount":0.0702},{"price":9955,"amount":0.01},{"price":9981,"amount":0.0376},{"price":9999,"amount":0.9003},{"price":10000,"amount":12.5032},{"price":10011,"amount":0.01},{"price":10050,"amount":6.01},{"price":10100,"amount":0.0295},{"price":10150,"amount":0.01},{"price":10200,"amount":0.02},{"price":10250,"amount":0.01},{"price":10300,"amount":0.02},{"price":10350,"amount":0.01},{"price":10400,"amount":0.03},{"price":10450,"amount":0.01},{"price":10487,"amount":0.45},{"price":10500,"amount":6.04},{"price":10580,"amount":0.5},{"price":10600,"amount":0.03},{"price":10700,"amount":0.03},{"price":10800,"amount":0.02},{"price":10900,"amount":0.1192},{"price":11000,"amount":6.2551},{"price":11100,"amount":0.01},{"price":11200,"amount":0.03},{"price":11258,"amount":0.5},{"price":11300,"amount":0.04},{"price":11400,"amount":0.04},{"price":11500,"amount":0.08},{"price":11600,"amount":0.02},{"price":11700,"amount":0.02},{"price":11800,"amount":0.02},{"price":11900,"amount":0.04},{"price":12000,"amount":1.07},{"price":12100,"amount":0.01},{"price":12200,"amount":0.04},{"price":12400,"amount":0.01},{"price":12401.59,"amount":0.4682},{"price":12500,"amount":0.07},{"price":12600,"amount":0.03},{"price":12800,"amount":0.03},{"price":13000,"amount":0.6202},{"price":13100,"amount":0.04},{"price":13200,"amount":0.01},{"price":13400,"amount":0.04},{"price":13500,"amount":0.03},{"price":13600,"amount":0.02},{"price":13700,"amount":0.04},{"price":13800,"amount":0.04},{"price":13804,"amount":0.1},{"price":13904,"amount":0.1},{"price":14000,"amount":0.55},{"price":14004,"amount":0.1},{"price":14104,"amount":0.1},{"price":14204,"amount":0.1},{"price":14304,"amount":0.1},{"price":14400,"amount":0.04},{"price":14404,"amount":0.1},{"price":14500,"amount":0.03},{"price":14504,"amount":0.1},{"price":14604,"amount":0.1},{"price":14638,"amount":0.056},{"price":14704,"amount":0.1},{"price":14800,"amount":0.01},{"price":14804,"amount":0.1},{"price":14904,"amount":0.1},{"price":15000,"amount":0.1332},{"price":15004,"amount":0.1},{"price":15104,"amount":0.1},{"price":15200,"amount":0.106},{"price":15204,"amount":0.1},{"price":15304,"amount":0.1},{"price":15378.08,"amount":0.1119},{"price":15404,"amount":0.1},{"price":15500,"amount":0.03},{"price":15504,"amount":0.1},{"price":15600,"amount":0.01},{"price":15604,"amount":0.1},{"price":15704,"amount":0.1},{"price":15804,"amount":0.1},{"price":15904,"amount":0.1},{"price":16000,"amount":0.07},{"price":16004,"amount":0.1},{"price":16104,"amount":0.1},{"price":16204,"amount":0.1},{"price":16304,"amount":0.1},{"price":16404,"amount":0.1},{"price":16500,"amount":0.02},{"price":16504,"amount":0.1},{"price":16604,"amount":0.1},{"price":16704,"amount":0.1},{"price":16804,"amount":0.1},{"price":16904,"amount":0.1},{"price":17000,"amount":0.28},{"price":17004,"amount":0.1},{"price":17104,"amount":0.1},{"price":17204,"amount":0.1},{"price":17251,"amount":0.056},{"price":17304,"amount":0.1},{"price":17404,"amount":0.1},{"price":17504,"amount":0.1},{"price":17604,"amount":0.1},{"price":17704,"amount":0.1},{"price":17804,"amount":0.1},{"price":17900,"amount":0.02},{"price":17904,"amount":0.1},{"price":18000,"amount":0.02},{"price":18004,"amount":0.1},{"price":18104,"amount":0.1}],"timestamp":1595254260473,"datetime":"2020-07-20T14:11:00.473Z"}},"trades":{"statusCode":200,"response":[{"id":"1879457","info":{"time":"2020-07-20T13:16:26.638Z","timestamp":"2020-07-20T13:16:26.638Z","trade_id":"1879457","price":"9157.88","size":"0.0109","side":"sell"},"timestamp":1595250986638,"datetime":"2020-07-20T13:16:26.638Z","symbol":"BTC/USD","side":"sell","price":9157.88,"amount":0.0109},{"id":"1879458","info":{"time":"2020-07-20T13:16:26.638Z","timestamp":"2020-07-20T13:16:26.638Z","trade_id":"1879458","price":"9157.88","size":"0.3151","side":"sell"},"timestamp":1595250986638,"datetime":"2020-07-20T13:16:26.638Z","symbol":"BTC/USD","side":"sell","price":9157.88,"amount":0.3151},{"id":"1879459","info":{"time":"2020-07-20T13:16:27.180Z","timestamp":"2020-07-20T13:16:27.180Z","trade_id":"1879459","price":"9157.88","size":"0.255","side":"sell"},"timestamp":1595250987180,"datetime":"2020-07-20T13:16:27.180Z","symbol":"BTC/USD","side":"sell","price":9157.88,"amount":0.255},{"id":"1879460","info":{"time":"2020-07-20T13:17:29.531Z","timestamp":"2020-07-20T13:17:29.531Z","trade_id":"1879460","price":"9155.98","size":"0.231","side":"sell"},"timestamp":1595251049531,"datetime":"2020-07-20T13:17:29.531Z","symbol":"BTC/USD","side":"sell","price":9155.98,"amount":0.231},{"id":"1879461","info":{"time":"2020-07-20T13:20:21.702Z","timestamp":"2020-07-20T13:20:21.702Z","trade_id":"1879461","price":"9155.93","size":"0.0092","side":"sell"},"timestamp":1595251221702,"datetime":"2020-07-20T13:20:21.702Z","symbol":"BTC/USD","side":"sell","price":9155.93,"amount":0.0092},{"id":"1879462","info":{"time":"2020-07-20T13:20:46.205Z","timestamp":"2020-07-20T13:20:46.205Z","trade_id":"1879462","price":"9155.94","size":"0.1103","side":"buy"},"timestamp":1595251246205,"datetime":"2020-07-20T13:20:46.205Z","symbol":"BTC/USD","side":"buy","price":9155.94,"amount":0.1103},{"id":"1879463","info":{"time":"2020-07-20T13:21:00.730Z","timestamp":"2020-07-20T13:21:00.730Z","trade_id":"1879463","price":"9155.93","size":"0.0017","side":"sell"},"timestamp":1595251260730,"datetime":"2020-07-20T13:21:00.730Z","symbol":"BTC/USD","side":"sell","price":9155.93,"amount":0.0017},{"id":"1879464","info":{"time":"2020-07-20T13:21:00.730Z","timestamp":"2020-07-20T13:21:00.730Z","trade_id":"1879464","price":"9155.93","size":"0.0188","side":"sell"},"timestamp":1595251260730,"datetime":"2020-07-20T13:21:00.730Z","symbol":"BTC/USD","side":"sell","price":9155.93,"amount":0.0188},{"id":"1879465","info":{"time":"2020-07-20T13:21:40.855Z","timestamp":"2020-07-20T13:21:40.855Z","trade_id":"1879465","price":"9155.93","size":"0.1093","side":"sell"},"timestamp":1595251300855,"datetime":"2020-07-20T13:21:40.855Z","symbol":"BTC/USD","side":"sell","price":9155.93,"amount":0.1093},{"id":"1879466","info":{"time":"2020-07-20T13:22:27.546Z","timestamp":"2020-07-20T13:22:27.546Z","trade_id":"1879466","price":"9155.94","size":"0.0526","side":"buy"},"timestamp":1595251347546,"datetime":"2020-07-20T13:22:27.546Z","symbol":"BTC/USD","side":"buy","price":9155.94,"amount":0.0526},{"id":"1879467","info":{"time":"2020-07-20T13:22:27.780Z","timestamp":"2020-07-20T13:22:27.780Z","trade_id":"1879467","price":"9155.94","size":"0.0048","side":"buy"},"timestamp":1595251347780,"datetime":"2020-07-20T13:22:27.780Z","symbol":"BTC/USD","side":"buy","price":9155.94,"amount":0.0048},{"id":"1879468","info":{"time":"2020-07-20T13:23:08.276Z","timestamp":"2020-07-20T13:23:08.276Z","trade_id":"1879468","price":"9155.94","size":"0.0075","side":"buy"},"timestamp":1595251388276,"datetime":"2020-07-20T13:23:08.276Z","symbol":"BTC/USD","side":"buy","price":9155.94,"amount":0.0075},{"id":"1879470","info":{"time":"2020-07-20T13:23:17.147Z","timestamp":"2020-07-20T13:23:17.147Z","trade_id":"1879470","price":"9155.93","size":"0.2991","side":"sell"},"timestamp":1595251397147,"datetime":"2020-07-20T13:23:17.147Z","symbol":"BTC/USD","side":"sell","price":9155.93,"amount":0.2991},{"id":"1879469","info":{"time":"2020-07-20T13:23:17.147Z","timestamp":"2020-07-20T13:23:17.147Z","trade_id":"1879469","price":"9155.93","size":"0.0109","side":"sell"},"timestamp":1595251397147,"datetime":"2020-07-20T13:23:17.147Z","symbol":"BTC/USD","side":"sell","price":9155.93,"amount":0.0109},{"id":"1879471","info":{"time":"2020-07-20T13:23:17.207Z","timestamp":"2020-07-20T13:23:17.207Z","trade_id":"1879471","price":"9155.93","size":"0.66","side":"sell"},"timestamp":1595251397207,"datetime":"2020-07-20T13:23:17.207Z","symbol":"BTC/USD","side":"sell","price":9155.93,"amount":0.66},{"id":"1879472","info":{"time":"2020-07-20T13:23:17.305Z","timestamp":"2020-07-20T13:23:17.305Z","trade_id":"1879472","price":"9155.93","size":"0.133","side":"sell"},"timestamp":1595251397305,"datetime":"2020-07-20T13:23:17.305Z","symbol":"BTC/USD","side":"sell","price":9155.93,"amount":0.133},{"id":"1879473","info":{"time":"2020-07-20T13:23:17.305Z","timestamp":"2020-07-20T13:23:17.305Z","trade_id":"1879473","price":"9155.93","size":"0.527","side":"sell"},"timestamp":1595251397305,"datetime":"2020-07-20T13:23:17.305Z","symbol":"BTC/USD","side":"sell","price":9155.93,"amount":0.527},{"id":"1879474","info":{"time":"2020-07-20T13:23:17.935Z","timestamp":"2020-07-20T13:23:17.935Z","trade_id":"1879474","price":"9152.52","size":"0.006","side":"buy"},"timestamp":1595251397935,"datetime":"2020-07-20T13:23:17.935Z","symbol":"BTC/USD","side":"buy","price":9152.52,"amount":0.006},{"id":"1879475","info":{"time":"2020-07-20T13:23:50.854Z","timestamp":"2020-07-20T13:23:50.854Z","trade_id":"1879475","price":"9152.51","size":"0.1744","side":"sell"},"timestamp":1595251430854,"datetime":"2020-07-20T13:23:50.854Z","symbol":"BTC/USD","side":"sell","price":9152.51,"amount":0.1744},{"id":"1879476","info":{"time":"2020-07-20T13:23:52.801Z","timestamp":"2020-07-20T13:23:52.801Z","trade_id":"1879476","price":"9152.52","size":"0.0391","side":"buy"},"timestamp":1595251432801,"datetime":"2020-07-20T13:23:52.801Z","symbol":"BTC/USD","side":"buy","price":9152.52,"amount":0.0391},{"id":"1879477","info":{"time":"2020-07-20T13:24:39.420Z","timestamp":"2020-07-20T13:24:39.420Z","trade_id":"1879477","price":"9152.51","size":"0.03","side":"sell"},"timestamp":1595251479420,"datetime":"2020-07-20T13:24:39.420Z","symbol":"BTC/USD","side":"sell","price":9152.51,"amount":0.03},{"id":"1879478","info":{"time":"2020-07-20T13:25:26.859Z","timestamp":"2020-07-20T13:25:26.859Z","trade_id":"1879478","price":"9152.51","size":"0.0171","side":"sell"},"timestamp":1595251526859,"datetime":"2020-07-20T13:25:26.859Z","symbol":"BTC/USD","side":"sell","price":9152.51,"amount":0.0171},{"id":"1879479","info":{"time":"2020-07-20T13:25:51.898Z","timestamp":"2020-07-20T13:25:51.898Z","trade_id":"1879479","price":"9152.51","size":"0.0138","side":"sell"},"timestamp":1595251551898,"datetime":"2020-07-20T13:25:51.898Z","symbol":"BTC/USD","side":"sell","price":9152.51,"amount":0.0138},{"id":"1879480","info":{"time":"2020-07-20T13:26:18.149Z","timestamp":"2020-07-20T13:26:18.149Z","trade_id":"1879480","price":"9153.29","size":"0.0119","side":"sell"},"timestamp":1595251578149,"datetime":"2020-07-20T13:26:18.149Z","symbol":"BTC/USD","side":"sell","price":9153.29,"amount":0.0119},{"id":"1879481","info":{"time":"2020-07-20T13:27:11.358Z","timestamp":"2020-07-20T13:27:11.358Z","trade_id":"1879481","price":"9153.3","size":"0.0036","side":"buy"},"timestamp":1595251631358,"datetime":"2020-07-20T13:27:11.358Z","symbol":"BTC/USD","side":"buy","price":9153.3,"amount":0.0036},{"id":"1879482","info":{"time":"2020-07-20T13:28:40.924Z","timestamp":"2020-07-20T13:28:40.924Z","trade_id":"1879482","price":"9153.29","size":"0.0881","side":"sell"},"timestamp":1595251720924,"datetime":"2020-07-20T13:28:40.924Z","symbol":"BTC/USD","side":"sell","price":9153.29,"amount":0.0881},{"id":"1879483","info":{"time":"2020-07-20T13:29:08.249Z","timestamp":"2020-07-20T13:29:08.249Z","trade_id":"1879483","price":"9153.29","size":"0.0117","side":"sell"},"timestamp":1595251748249,"datetime":"2020-07-20T13:29:08.249Z","symbol":"BTC/USD","side":"sell","price":9153.29,"amount":0.0117},{"id":"1879484","info":{"time":"2020-07-20T13:31:38.830Z","timestamp":"2020-07-20T13:31:38.830Z","trade_id":"1879484","price":"9153.3","size":"0.0031","side":"buy"},"timestamp":1595251898830,"datetime":"2020-07-20T13:31:38.830Z","symbol":"BTC/USD","side":"buy","price":9153.3,"amount":0.0031},{"id":"1879485","info":{"time":"2020-07-20T13:32:05.862Z","timestamp":"2020-07-20T13:32:05.862Z","trade_id":"1879485","price":"9153.29","size":"0.6345","side":"sell"},"timestamp":1595251925862,"datetime":"2020-07-20T13:32:05.862Z","symbol":"BTC/USD","side":"sell","price":9153.29,"amount":0.6345},{"id":"1879486","info":{"time":"2020-07-20T13:32:25.198Z","timestamp":"2020-07-20T13:32:25.198Z","trade_id":"1879486","price":"9153.3","size":"0.5003","side":"buy"},"timestamp":1595251945198,"datetime":"2020-07-20T13:32:25.198Z","symbol":"BTC/USD","side":"buy","price":9153.3,"amount":0.5003},{"id":"1879487","info":{"time":"2020-07-20T13:32:29.002Z","timestamp":"2020-07-20T13:32:29.002Z","trade_id":"1879487","price":"9154.31","size":"0.4164","side":"buy"},"timestamp":1595251949002,"datetime":"2020-07-20T13:32:29.002Z","symbol":"BTC/USD","side":"buy","price":9154.31,"amount":0.4164},{"id":"1879488","info":{"time":"2020-07-20T13:32:29.554Z","timestamp":"2020-07-20T13:32:29.554Z","trade_id":"1879488","price":"9157.19","size":"0.01","side":"buy"},"timestamp":1595251949554,"datetime":"2020-07-20T13:32:29.554Z","symbol":"BTC/USD","side":"buy","price":9157.19,"amount":0.01},{"id":"1879489","info":{"time":"2020-07-20T13:32:30.581Z","timestamp":"2020-07-20T13:32:30.581Z","trade_id":"1879489","price":"9158.09","size":"0.004","side":"buy"},"timestamp":1595251950581,"datetime":"2020-07-20T13:32:30.581Z","symbol":"BTC/USD","side":"buy","price":9158.09,"amount":0.004},{"id":"1879490","info":{"time":"2020-07-20T13:32:30.898Z","timestamp":"2020-07-20T13:32:30.898Z","trade_id":"1879490","price":"9158.38","size":"0.007","side":"buy"},"timestamp":1595251950898,"datetime":"2020-07-20T13:32:30.898Z","symbol":"BTC/USD","side":"buy","price":9158.38,"amount":0.007},{"id":"1879491","info":{"time":"2020-07-20T13:32:30.898Z","timestamp":"2020-07-20T13:32:30.898Z","trade_id":"1879491","price":"9158.39","size":"0.085","side":"buy"},"timestamp":1595251950898,"datetime":"2020-07-20T13:32:30.898Z","symbol":"BTC/USD","side":"buy","price":9158.39,"amount":0.085},{"id":"1879492","info":{"time":"2020-07-20T13:32:30.898Z","timestamp":"2020-07-20T13:32:30.898Z","trade_id":"1879492","price":"9158.4","size":"0.1198","side":"buy"},"timestamp":1595251950898,"datetime":"2020-07-20T13:32:30.898Z","symbol":"BTC/USD","side":"buy","price":9158.4,"amount":0.1198},{"id":"1879493","info":{"time":"2020-07-20T13:33:00.622Z","timestamp":"2020-07-20T13:33:00.622Z","trade_id":"1879493","price":"9158.1","size":"0.0234","side":"buy"},"timestamp":1595251980622,"datetime":"2020-07-20T13:33:00.622Z","symbol":"BTC/USD","side":"buy","price":9158.1,"amount":0.0234},{"id":"1879494","info":{"time":"2020-07-20T13:33:25.326Z","timestamp":"2020-07-20T13:33:25.326Z","trade_id":"1879494","price":"9158.1","size":"0.0017","side":"buy"},"timestamp":1595252005326,"datetime":"2020-07-20T13:33:25.326Z","symbol":"BTC/USD","side":"buy","price":9158.1,"amount":0.0017},{"id":"1879495","info":{"time":"2020-07-20T13:33:53.729Z","timestamp":"2020-07-20T13:33:53.729Z","trade_id":"1879495","price":"9158.1","size":"0.0083","side":"buy"},"timestamp":1595252033729,"datetime":"2020-07-20T13:33:53.729Z","symbol":"BTC/USD","side":"buy","price":9158.1,"amount":0.0083},{"id":"1879496","info":{"time":"2020-07-20T13:33:53.729Z","timestamp":"2020-07-20T13:33:53.729Z","trade_id":"1879496","price":"9158.1","size":"0.0081","side":"buy"},"timestamp":1595252033729,"datetime":"2020-07-20T13:33:53.729Z","symbol":"BTC/USD","side":"buy","price":9158.1,"amount":0.0081},{"id":"1879497","info":{"time":"2020-07-20T13:34:21.793Z","timestamp":"2020-07-20T13:34:21.793Z","trade_id":"1879497","price":"9158.1","size":"0.007","side":"buy"},"timestamp":1595252061793,"datetime":"2020-07-20T13:34:21.793Z","symbol":"BTC/USD","side":"buy","price":9158.1,"amount":0.007},{"id":"1879498","info":{"time":"2020-07-20T13:34:33.807Z","timestamp":"2020-07-20T13:34:33.807Z","trade_id":"1879498","price":"9158.53","size":"0.1799","side":"buy"},"timestamp":1595252073807,"datetime":"2020-07-20T13:34:33.807Z","symbol":"BTC/USD","side":"buy","price":9158.53,"amount":0.1799},{"id":"1879499","info":{"time":"2020-07-20T13:34:45.454Z","timestamp":"2020-07-20T13:34:45.454Z","trade_id":"1879499","price":"9158.53","size":"0.01","side":"buy"},"timestamp":1595252085454,"datetime":"2020-07-20T13:34:45.454Z","symbol":"BTC/USD","side":"buy","price":9158.53,"amount":0.01},{"id":"1879500","info":{"time":"2020-07-20T13:34:45.454Z","timestamp":"2020-07-20T13:34:45.454Z","trade_id":"1879500","price":"9158.53","size":"0.0201","side":"buy"},"timestamp":1595252085454,"datetime":"2020-07-20T13:34:45.454Z","symbol":"BTC/USD","side":"buy","price":9158.53,"amount":0.0201},{"id":"1879501","info":{"time":"2020-07-20T13:35:05.569Z","timestamp":"2020-07-20T13:35:05.569Z","trade_id":"1879501","price":"9158.53","size":"0.004","side":"buy"},"timestamp":1595252105569,"datetime":"2020-07-20T13:35:05.569Z","symbol":"BTC/USD","side":"buy","price":9158.53,"amount":0.004},{"id":"1879502","info":{"time":"2020-07-20T13:35:09.874Z","timestamp":"2020-07-20T13:35:09.874Z","trade_id":"1879502","price":"9158.84","size":"0.002","side":"buy"},"timestamp":1595252109874,"datetime":"2020-07-20T13:35:09.874Z","symbol":"BTC/USD","side":"buy","price":9158.84,"amount":0.002},{"id":"1879503","info":{"time":"2020-07-20T13:35:31.065Z","timestamp":"2020-07-20T13:35:31.065Z","trade_id":"1879503","price":"9158.11","size":"0.006","side":"buy"},"timestamp":1595252131065,"datetime":"2020-07-20T13:35:31.065Z","symbol":"BTC/USD","side":"buy","price":9158.11,"amount":0.006},{"id":"1879504","info":{"time":"2020-07-20T13:35:35.324Z","timestamp":"2020-07-20T13:35:35.324Z","trade_id":"1879504","price":"9158.83","size":"0.007","side":"buy"},"timestamp":1595252135324,"datetime":"2020-07-20T13:35:35.324Z","symbol":"BTC/USD","side":"buy","price":9158.83,"amount":0.007},{"id":"1879505","info":{"time":"2020-07-20T13:35:35.324Z","timestamp":"2020-07-20T13:35:35.324Z","trade_id":"1879505","price":"9158.83","size":"0.043","side":"buy"},"timestamp":1595252135324,"datetime":"2020-07-20T13:35:35.324Z","symbol":"BTC/USD","side":"buy","price":9158.83,"amount":0.043},{"id":"1879506","info":{"time":"2020-07-20T13:36:15.701Z","timestamp":"2020-07-20T13:36:15.701Z","trade_id":"1879506","price":"9158.83","size":"0.0012","side":"buy"},"timestamp":1595252175701,"datetime":"2020-07-20T13:36:15.701Z","symbol":"BTC/USD","side":"buy","price":9158.83,"amount":0.0012},{"id":"1879507","info":{"time":"2020-07-20T13:39:00.709Z","timestamp":"2020-07-20T13:39:00.709Z","trade_id":"1879507","price":"9158.1","size":"0.0125","side":"buy"},"timestamp":1595252340709,"datetime":"2020-07-20T13:39:00.709Z","symbol":"BTC/USD","side":"buy","price":9158.1,"amount":0.0125},{"id":"1879508","info":{"time":"2020-07-20T13:39:50.375Z","timestamp":"2020-07-20T13:39:50.375Z","trade_id":"1879508","price":"9158.09","size":"0.0109","side":"sell"},"timestamp":1595252390375,"datetime":"2020-07-20T13:39:50.375Z","symbol":"BTC/USD","side":"sell","price":9158.09,"amount":0.0109},{"id":"1879509","info":{"time":"2020-07-20T13:39:50.375Z","timestamp":"2020-07-20T13:39:50.375Z","trade_id":"1879509","price":"9158.09","size":"0.0321","side":"sell"},"timestamp":1595252390375,"datetime":"2020-07-20T13:39:50.375Z","symbol":"BTC/USD","side":"sell","price":9158.09,"amount":0.0321},{"id":"1879510","info":{"time":"2020-07-20T13:42:24.393Z","timestamp":"2020-07-20T13:42:24.393Z","trade_id":"1879510","price":"9157.06","size":"0.0109","side":"sell"},"timestamp":1595252544393,"datetime":"2020-07-20T13:42:24.393Z","symbol":"BTC/USD","side":"sell","price":9157.06,"amount":0.0109},{"id":"1879511","info":{"time":"2020-07-20T13:44:32.874Z","timestamp":"2020-07-20T13:44:32.874Z","trade_id":"1879511","price":"9154.65","size":"0.0109","side":"sell"},"timestamp":1595252672874,"datetime":"2020-07-20T13:44:32.874Z","symbol":"BTC/USD","side":"sell","price":9154.65,"amount":0.0109},{"id":"1879512","info":{"time":"2020-07-20T13:44:32.874Z","timestamp":"2020-07-20T13:44:32.874Z","trade_id":"1879512","price":"9154.65","size":"1.09","side":"sell"},"timestamp":1595252672874,"datetime":"2020-07-20T13:44:32.874Z","symbol":"BTC/USD","side":"sell","price":9154.65,"amount":1.09},{"id":"1879513","info":{"time":"2020-07-20T13:45:17.953Z","timestamp":"2020-07-20T13:45:17.953Z","trade_id":"1879513","price":"9154.07","size":"0.0913","side":"sell"},"timestamp":1595252717953,"datetime":"2020-07-20T13:45:17.953Z","symbol":"BTC/USD","side":"sell","price":9154.07,"amount":0.0913},{"id":"1879514","info":{"time":"2020-07-20T13:45:17.953Z","timestamp":"2020-07-20T13:45:17.953Z","trade_id":"1879514","price":"9154.07","size":"0.0109","side":"sell"},"timestamp":1595252717953,"datetime":"2020-07-20T13:45:17.953Z","symbol":"BTC/USD","side":"sell","price":9154.07,"amount":0.0109},{"id":"1879515","info":{"time":"2020-07-20T13:46:19.226Z","timestamp":"2020-07-20T13:46:19.226Z","trade_id":"1879515","price":"9151.55","size":"0.0035","side":"sell"},"timestamp":1595252779226,"datetime":"2020-07-20T13:46:19.226Z","symbol":"BTC/USD","side":"sell","price":9151.55,"amount":0.0035},{"id":"1879516","info":{"time":"2020-07-20T13:48:03.190Z","timestamp":"2020-07-20T13:48:03.190Z","trade_id":"1879516","price":"9151.55","size":"0.0074","side":"sell"},"timestamp":1595252883190,"datetime":"2020-07-20T13:48:03.190Z","symbol":"BTC/USD","side":"sell","price":9151.55,"amount":0.0074},{"id":"1879517","info":{"time":"2020-07-20T13:49:27.291Z","timestamp":"2020-07-20T13:49:27.291Z","trade_id":"1879517","price":"9150.06","size":"0.0109","side":"sell"},"timestamp":1595252967291,"datetime":"2020-07-20T13:49:27.291Z","symbol":"BTC/USD","side":"sell","price":9150.06,"amount":0.0109},{"id":"1879518","info":{"time":"2020-07-20T13:49:27.442Z","timestamp":"2020-07-20T13:49:27.442Z","trade_id":"1879518","price":"9150.06","size":"0.66","side":"sell"},"timestamp":1595252967442,"datetime":"2020-07-20T13:49:27.442Z","symbol":"BTC/USD","side":"sell","price":9150.06,"amount":0.66},{"id":"1879519","info":{"time":"2020-07-20T13:49:35.608Z","timestamp":"2020-07-20T13:49:35.608Z","trade_id":"1879519","price":"9148.15","size":"0.014","side":"sell"},"timestamp":1595252975608,"datetime":"2020-07-20T13:49:35.608Z","symbol":"BTC/USD","side":"sell","price":9148.15,"amount":0.014},{"id":"1879520","info":{"time":"2020-07-20T13:50:11.638Z","timestamp":"2020-07-20T13:50:11.638Z","trade_id":"1879520","price":"9148.15","size":"0.0191","side":"sell"},"timestamp":1595253011638,"datetime":"2020-07-20T13:50:11.638Z","symbol":"BTC/USD","side":"sell","price":9148.15,"amount":0.0191},{"id":"1879521","info":{"time":"2020-07-20T13:50:16.682Z","timestamp":"2020-07-20T13:50:16.682Z","trade_id":"1879521","price":"9148.16","size":"0.01","side":"buy"},"timestamp":1595253016682,"datetime":"2020-07-20T13:50:16.682Z","symbol":"BTC/USD","side":"buy","price":9148.16,"amount":0.01},{"id":"1879522","info":{"time":"2020-07-20T13:51:36.545Z","timestamp":"2020-07-20T13:51:36.545Z","trade_id":"1879522","price":"9148.15","size":"0.0109","side":"sell"},"timestamp":1595253096545,"datetime":"2020-07-20T13:51:36.545Z","symbol":"BTC/USD","side":"sell","price":9148.15,"amount":0.0109},{"id":"1879523","info":{"time":"2020-07-20T13:51:49.491Z","timestamp":"2020-07-20T13:51:49.491Z","trade_id":"1879523","price":"9145.51","size":"0.0109","side":"sell"},"timestamp":1595253109491,"datetime":"2020-07-20T13:51:49.491Z","symbol":"BTC/USD","side":"sell","price":9145.51,"amount":0.0109},{"id":"1879524","info":{"time":"2020-07-20T13:51:49.597Z","timestamp":"2020-07-20T13:51:49.597Z","trade_id":"1879524","price":"9144.48","size":"0.115","side":"sell"},"timestamp":1595253109597,"datetime":"2020-07-20T13:51:49.597Z","symbol":"BTC/USD","side":"sell","price":9144.48,"amount":0.115},{"id":"1879525","info":{"time":"2020-07-20T13:52:52.530Z","timestamp":"2020-07-20T13:52:52.530Z","trade_id":"1879525","price":"9144.51","size":"0.0044","side":"buy"},"timestamp":1595253172530,"datetime":"2020-07-20T13:52:52.530Z","symbol":"BTC/USD","side":"buy","price":9144.51,"amount":0.0044},{"id":"1879526","info":{"time":"2020-07-20T13:55:31.259Z","timestamp":"2020-07-20T13:55:31.259Z","trade_id":"1879526","price":"9145.21","size":"0.0012","side":"buy"},"timestamp":1595253331259,"datetime":"2020-07-20T13:55:31.259Z","symbol":"BTC/USD","side":"buy","price":9145.21,"amount":0.0012},{"id":"1879527","info":{"time":"2020-07-20T13:56:40.021Z","timestamp":"2020-07-20T13:56:40.021Z","trade_id":"1879527","price":"9146.1","size":"0.115","side":"sell"},"timestamp":1595253400021,"datetime":"2020-07-20T13:56:40.021Z","symbol":"BTC/USD","side":"sell","price":9146.1,"amount":0.115},{"id":"1879528","info":{"time":"2020-07-20T13:57:00.578Z","timestamp":"2020-07-20T13:57:00.578Z","trade_id":"1879528","price":"9146.11","size":"0.1151","side":"buy"},"timestamp":1595253420578,"datetime":"2020-07-20T13:57:00.578Z","symbol":"BTC/USD","side":"buy","price":9146.11,"amount":0.1151},{"id":"1879529","info":{"time":"2020-07-20T13:57:19.760Z","timestamp":"2020-07-20T13:57:19.760Z","trade_id":"1879529","price":"9146.11","size":"0.0194","side":"buy"},"timestamp":1595253439760,"datetime":"2020-07-20T13:57:19.760Z","symbol":"BTC/USD","side":"buy","price":9146.11,"amount":0.0194},{"id":"1879530","info":{"time":"2020-07-20T13:59:12.915Z","timestamp":"2020-07-20T13:59:12.915Z","trade_id":"1879530","price":"9146.11","size":"0.0075","side":"buy"},"timestamp":1595253552915,"datetime":"2020-07-20T13:59:12.915Z","symbol":"BTC/USD","side":"buy","price":9146.11,"amount":0.0075},{"id":"1879531","info":{"time":"2020-07-20T13:59:21.226Z","timestamp":"2020-07-20T13:59:21.226Z","trade_id":"1879531","price":"9146.11","size":"0.0062","side":"buy"},"timestamp":1595253561226,"datetime":"2020-07-20T13:59:21.226Z","symbol":"BTC/USD","side":"buy","price":9146.11,"amount":0.0062},{"id":"1879532","info":{"time":"2020-07-20T14:01:10.507Z","timestamp":"2020-07-20T14:01:10.507Z","trade_id":"1879532","price":"9146.1","size":"0.0111","side":"sell"},"timestamp":1595253670507,"datetime":"2020-07-20T14:01:10.507Z","symbol":"BTC/USD","side":"sell","price":9146.1,"amount":0.0111},{"id":"1879533","info":{"time":"2020-07-20T14:01:30.378Z","timestamp":"2020-07-20T14:01:30.378Z","trade_id":"1879533","price":"9146.1","size":"0.836","side":"sell"},"timestamp":1595253690378,"datetime":"2020-07-20T14:01:30.378Z","symbol":"BTC/USD","side":"sell","price":9146.1,"amount":0.836},{"id":"1879534","info":{"time":"2020-07-20T14:01:35.441Z","timestamp":"2020-07-20T14:01:35.441Z","trade_id":"1879534","price":"9146.1","size":"0.012","side":"sell"},"timestamp":1595253695441,"datetime":"2020-07-20T14:01:35.441Z","symbol":"BTC/USD","side":"sell","price":9146.1,"amount":0.012},{"id":"1879535","info":{"time":"2020-07-20T14:01:36.789Z","timestamp":"2020-07-20T14:01:36.789Z","trade_id":"1879535","price":"9146.11","size":"0.01","side":"buy"},"timestamp":1595253696789,"datetime":"2020-07-20T14:01:36.789Z","symbol":"BTC/USD","side":"buy","price":9146.11,"amount":0.01},{"id":"1879536","info":{"time":"2020-07-20T14:01:56.685Z","timestamp":"2020-07-20T14:01:56.685Z","trade_id":"1879536","price":"9146.1","size":"0.0135","side":"sell"},"timestamp":1595253716685,"datetime":"2020-07-20T14:01:56.685Z","symbol":"BTC/USD","side":"sell","price":9146.1,"amount":0.0135},{"id":"1879537","info":{"time":"2020-07-20T14:02:10.633Z","timestamp":"2020-07-20T14:02:10.633Z","trade_id":"1879537","price":"9146.11","size":"0.0062","side":"buy"},"timestamp":1595253730633,"datetime":"2020-07-20T14:02:10.633Z","symbol":"BTC/USD","side":"buy","price":9146.11,"amount":0.0062},{"id":"1879538","info":{"time":"2020-07-20T14:02:21.560Z","timestamp":"2020-07-20T14:02:21.560Z","trade_id":"1879538","price":"9146.11","size":"0.0062","side":"buy"},"timestamp":1595253741560,"datetime":"2020-07-20T14:02:21.560Z","symbol":"BTC/USD","side":"buy","price":9146.11,"amount":0.0062},{"id":"1879539","info":{"time":"2020-07-20T14:03:11.794Z","timestamp":"2020-07-20T14:03:11.794Z","trade_id":"1879539","price":"9146.1","size":"0.1105","side":"sell"},"timestamp":1595253791794,"datetime":"2020-07-20T14:03:11.794Z","symbol":"BTC/USD","side":"sell","price":9146.1,"amount":0.1105},{"id":"1879540","info":{"time":"2020-07-20T14:03:12.913Z","timestamp":"2020-07-20T14:03:12.913Z","trade_id":"1879540","price":"9146.11","size":"0.0022","side":"buy"},"timestamp":1595253792913,"datetime":"2020-07-20T14:03:12.913Z","symbol":"BTC/USD","side":"buy","price":9146.11,"amount":0.0022},{"id":"1879541","info":{"time":"2020-07-20T14:03:42.129Z","timestamp":"2020-07-20T14:03:42.129Z","trade_id":"1879541","price":"9146.11","size":"0.0058","side":"buy"},"timestamp":1595253822129,"datetime":"2020-07-20T14:03:42.129Z","symbol":"BTC/USD","side":"buy","price":9146.11,"amount":0.0058},{"id":"1879542","info":{"time":"2020-07-20T14:04:05.804Z","timestamp":"2020-07-20T14:04:05.804Z","trade_id":"1879542","price":"9146.65","size":"0.017","side":"buy"},"timestamp":1595253845804,"datetime":"2020-07-20T14:04:05.804Z","symbol":"BTC/USD","side":"buy","price":9146.65,"amount":0.017},{"id":"1879543","info":{"time":"2020-07-20T14:04:09.835Z","timestamp":"2020-07-20T14:04:09.835Z","trade_id":"1879543","price":"9146.65","size":"0.218","side":"buy"},"timestamp":1595253849835,"datetime":"2020-07-20T14:04:09.835Z","symbol":"BTC/USD","side":"buy","price":9146.65,"amount":0.218},{"id":"1879544","info":{"time":"2020-07-20T14:05:15.754Z","timestamp":"2020-07-20T14:05:15.754Z","trade_id":"1879544","price":"9149.41","size":"0.2184","side":"buy"},"timestamp":1595253915754,"datetime":"2020-07-20T14:05:15.754Z","symbol":"BTC/USD","side":"buy","price":9149.41,"amount":0.2184},{"id":"1879545","info":{"time":"2020-07-20T14:05:21.547Z","timestamp":"2020-07-20T14:05:21.547Z","trade_id":"1879545","price":"9149.41","size":"0.1675","side":"buy"},"timestamp":1595253921547,"datetime":"2020-07-20T14:05:21.547Z","symbol":"BTC/USD","side":"buy","price":9149.41,"amount":0.1675},{"id":"1879546","info":{"time":"2020-07-20T14:06:52.182Z","timestamp":"2020-07-20T14:06:52.182Z","trade_id":"1879546","price":"9157.45","size":"0.0312","side":"buy"},"timestamp":1595254012182,"datetime":"2020-07-20T14:06:52.182Z","symbol":"BTC/USD","side":"buy","price":9157.45,"amount":0.0312},{"id":"1879547","info":{"time":"2020-07-20T14:07:09.101Z","timestamp":"2020-07-20T14:07:09.101Z","trade_id":"1879547","price":"9158.42","size":"0.0018","side":"sell"},"timestamp":1595254029101,"datetime":"2020-07-20T14:07:09.101Z","symbol":"BTC/USD","side":"sell","price":9158.42,"amount":0.0018},{"id":"1879548","info":{"time":"2020-07-20T14:07:20.755Z","timestamp":"2020-07-20T14:07:20.755Z","trade_id":"1879548","price":"9158.43","size":"0.0545","side":"buy"},"timestamp":1595254040755,"datetime":"2020-07-20T14:07:20.755Z","symbol":"BTC/USD","side":"buy","price":9158.43,"amount":0.0545},{"id":"1879549","info":{"time":"2020-07-20T14:07:59.429Z","timestamp":"2020-07-20T14:07:59.429Z","trade_id":"1879549","price":"9157.6","size":"0.0014","side":"buy"},"timestamp":1595254079429,"datetime":"2020-07-20T14:07:59.429Z","symbol":"BTC/USD","side":"buy","price":9157.6,"amount":0.0014},{"id":"1879550","info":{"time":"2020-07-20T14:09:05.201Z","timestamp":"2020-07-20T14:09:05.201Z","trade_id":"1879550","price":"9158.92","size":"0.415","side":"sell"},"timestamp":1595254145201,"datetime":"2020-07-20T14:09:05.201Z","symbol":"BTC/USD","side":"sell","price":9158.92,"amount":0.415},{"id":"1879551","info":{"time":"2020-07-20T14:09:23.088Z","timestamp":"2020-07-20T14:09:23.088Z","trade_id":"1879551","price":"9158.93","size":"0.002","side":"buy"},"timestamp":1595254163088,"datetime":"2020-07-20T14:09:23.088Z","symbol":"BTC/USD","side":"buy","price":9158.93,"amount":0.002},{"id":"1879552","info":{"time":"2020-07-20T14:09:23.088Z","timestamp":"2020-07-20T14:09:23.088Z","trade_id":"1879552","price":"9158.93","size":"0.0037","side":"buy"},"timestamp":1595254163088,"datetime":"2020-07-20T14:09:23.088Z","symbol":"BTC/USD","side":"buy","price":9158.93,"amount":0.0037},{"id":"1879553","info":{"time":"2020-07-20T14:10:12.732Z","timestamp":"2020-07-20T14:10:12.732Z","trade_id":"1879553","price":"9160.31","size":"0.0109","side":"sell"},"timestamp":1595254212732,"datetime":"2020-07-20T14:10:12.732Z","symbol":"BTC/USD","side":"sell","price":9160.31,"amount":0.0109},{"id":"1879554","info":{"time":"2020-07-20T14:10:12.732Z","timestamp":"2020-07-20T14:10:12.732Z","trade_id":"1879554","price":"9160.31","size":"0.6002","side":"sell"},"timestamp":1595254212732,"datetime":"2020-07-20T14:10:12.732Z","symbol":"BTC/USD","side":"sell","price":9160.31,"amount":0.6002},{"id":"1879555","info":{"time":"2020-07-20T14:10:15.761Z","timestamp":"2020-07-20T14:10:15.761Z","trade_id":"1879555","price":"9160.3","size":"0.2359","side":"sell"},"timestamp":1595254215761,"datetime":"2020-07-20T14:10:15.761Z","symbol":"BTC/USD","side":"sell","price":9160.3,"amount":0.2359},{"id":"1879556","info":{"time":"2020-07-20T14:10:53.875Z","timestamp":"2020-07-20T14:10:53.875Z","trade_id":"1879556","price":"9160.3","size":"0.0063","side":"sell"},"timestamp":1595254253875,"datetime":"2020-07-20T14:10:53.875Z","symbol":"BTC/USD","side":"sell","price":9160.3,"amount":0.0063}]}}